README.rst
setup.py
spplib/__init__.py
spplib.egg-info/PKG-INFO
spplib.egg-info/SOURCES.txt
spplib.egg-info/dependency_links.txt
spplib.egg-info/entry_points.txt
spplib.egg-info/requires.txt
spplib.egg-info/top_level.txt
spplib/cli/__init__.py
spplib/cli/ecxcli.py
spplib/cli/util.py
spplib/cli/commands/__init__.py
spplib/cli/commands/cmd_job.py
spplib/cli/commands/cmd_logs.py
spplib/cli/commands/cmd_resource.py
spplib/cli/commands/cmd_sla.py
spplib/cli/commands/cmd_vm.py
spplib/sdk/__init__.py
spplib/sdk/client.py