Metadata-Version: 1.1
Name: spplib
Version: 0.55
Summary: A client for SPP
Home-page: UNKNOWN
Author: Ben Jones
Author-email: ben.jones@ibm.com
License: Apache License 2.0
Keywords: development
Platform: UNKNOWN
Classifier: Development Status :: 4 - Beta
Classifier: Intended Audience :: Developers
Classifier: Topic :: Software Development
Classifier: License :: OSI Approved :: Apache Software License
Classifier: Programming Language :: Python :: 3
Classifier: Programming Language :: Python :: 3.6
